pulp2mat/__init__.py
pulp2mat/lp2mat.py
pulp2mat-0.1.5.dist-info/METADATA
pulp2mat-0.1.5.dist-info/WHEEL
pulp2mat-0.1.5.dist-info/licenses/LICENSE
pulp2mat-0.1.5.dist-info/RECORD
